{
  "schema": "../schema.json",
  "tags": [],
  "name": "Bumper",
  "description": "",
  "eventDecorators": [],
  "functionDecorators": [
    {
      "signature": "addBump()",
      "name": "addBump",
      "description": "",
      "parameterDecorators": [],
      "returnDecorators": [],
      "emittableEvents": [],
      "readOnly": false
    },
    {
      "signature": "bumps(uint256)",
      "name": "bumps",
      "description": "",
      "parameterDecorators": [
        {
          "name": "param0",
          "description": "",
          "recommendedTypes": []
        }
      ],
      "returnDecorators": [
        {
          "name": "cat",
          "description": "",
          "recommendedTypes": [],
          "solidityType": "uint256"
        },
        {
          "name": "dog",
          "description": "",
          "recommendedTypes": [],
          "solidityType": "bool"
        },
        {
          "name": "name",
          "description": "",
          "recommendedTypes": [],
          "solidityType": "string"
        },
        {
          "name": "chair",
          "description": "",
          "recommendedTypes": [],
          "solidityType": "string"
        }
      ],
      "emittableEvents": [],
      "readOnly": true
    },
    {
      "signature": "getBumps()",
      "name": "getBumps",
      "description": "",
      "parameterDecorators": [],
      "returnDecorators": [
        {
          "name": "param0",
          "description": "",
          "recommendedTypes": [],
          "solidityType": "tuple[]"
        }
      ],
      "emittableEvents": [],
      "readOnly": true
    },
    {
      "signature": "governance()",
      "name": "governance",
      "description": "",
      "parameterDecorators": [],
      "returnDecorators": [
        {
          "name": "param0",
          "description": "",
          "recommendedTypes": [],
          "solidityType": "address"
        }
      ],
      "emittableEvents": [],
      "readOnly": true
    }
  ]
}