{
  "schema": "../schema.json",
  "tags": [],
  "name": "CreditFeeManager",
  "description": "",
  "eventDecorators": [
    {
      "signature": "FeesCollected(address,address,uint256)",
      "name": "FeesCollected",
      "description": "Triggered when some tokens have been unstaked.",
      "parameterDecorators": [
        {
          "name": "network",
          "description": "",
          "recommendedTypes": [],
          "indexed": false
        },
        {
          "name": "member",
          "description": "",
          "recommendedTypes": [],
          "indexed": false
        },
        {
          "name": "totalFee",
          "description": "",
          "recommendedTypes": [],
          "indexed": false
        }
      ]
    },
    {
      "signature": "OwnershipTransferred(address,address)",
      "name": "OwnershipTransferred",
      "description": "Triggered when some tokens have been unstaked.",
      "parameterDecorators": [
        {
          "name": "amount",
          "description": "Unstake amount.",
          "recommendedTypes": [],
          "indexed": true
        },
        {
          "name": "holder",
          "description": "Address of the holder.",
          "recommendedTypes": [],
          "indexed": true
        }
      ]
    },
    {
      "signature": "PoolRewardsUpdated(address,uint256)",
      "name": "PoolRewardsUpdated",
      "description": "Triggered when some tokens have been unstaked.",
      "parameterDecorators": [
        {
          "name": "amount",
          "description": "Unstake amount.",
          "recommendedTypes": [],
          "indexed": false
        },
        {
          "name": "holder",
          "description": "Address of the holder.",
          "recommendedTypes": [],
          "indexed": false
        }
      ]
    },
    {
      "signature": "UnderwriterRewardsStaked(address,uint256)",
      "name": "UnderwriterRewardsStaked",
      "description": "Triggered when some tokens have been unstaked.",
      "parameterDecorators": [
        {
          "name": "amount",
          "description": "Unstake amount.",
          "recommendedTypes": [],
          "indexed": false
        },
        {
          "name": "holder",
          "description": "Address of the holder.",
          "recommendedTypes": [],
          "indexed": false
        }
      ]
    }
  ],
  "functionDecorators": [
    {
      "signature": "approveCreditPool(address)",
      "name": "approveCreditPool",
      "description": "",
      "parameterDecorators": [
        {
          "name": "_pool",
          "description": "",
          "recommendedTypes": []
        }
      ],
      "returnDecorators": [],
      "emittableEvents": [],
      "readOnly": false
    },
    {
      "signature": "calculateFees(address,uint256)",
      "name": "calculateFees",
      "description": "",
      "parameterDecorators": [
        {
          "name": "_network",
          "description": "",
          "recommendedTypes": []
        },
        {
          "name": "_transactionAmount",
          "description": "",
          "recommendedTypes": []
        }
      ],
      "returnDecorators": [
        {
          "name": "creditFee",
          "description": "",
          "recommendedTypes": [],
          "solidityType": "uint256"
        }
      ],
      "emittableEvents": [],
      "readOnly": true
    },
    {
      "signature": "collateralToken()",
      "name": "collateralToken",
      "description": "",
      "parameterDecorators": [],
      "returnDecorators": [
        {
          "name": "param0",
          "description": "",
          "recommendedTypes": [],
          "solidityType": "address"
        }
      ],
      "emittableEvents": [],
      "readOnly": true
    },
    {
      "signature": "collectFees(address,address,uint256)",
      "name": "collectFees",
      "description": "",
      "parameterDecorators": [
        {
          "name": "_network",
          "description": "",
          "recommendedTypes": []
        },
        {
          "name": "_networkMember",
          "description": "",
          "recommendedTypes": []
        },
        {
          "name": "_transactionAmount",
          "description": "",
          "recommendedTypes": []
        }
      ],
      "returnDecorators": [],
      "emittableEvents": [],
      "readOnly": false
    },
    {
      "signature": "creditManager()",
      "name": "creditManager",
      "description": "",
      "parameterDecorators": [],
      "returnDecorators": [
        {
          "name": "param0",
          "description": "",
          "recommendedTypes": [],
          "solidityType": "address"
        }
      ],
      "emittableEvents": [],
      "readOnly": true
    },
    {
      "signature": "creditRequest()",
      "name": "creditRequest",
      "description": "",
      "parameterDecorators": [],
      "returnDecorators": [
        {
          "name": "param0",
          "description": "",
          "recommendedTypes": [],
          "solidityType": "address"
        }
      ],
      "emittableEvents": [],
      "readOnly": true
    },
    {
      "signature": "creditRoles()",
      "name": "creditRoles",
      "description": "",
      "parameterDecorators": [],
      "returnDecorators": [
        {
          "name": "param0",
          "description": "",
          "recommendedTypes": [],
          "solidityType": "address"
        }
      ],
      "emittableEvents": [],
      "readOnly": true
    },
    {
      "signature": "distributeFees(address,address[])",
      "name": "distributeFees",
      "description": "",
      "parameterDecorators": [
        {
          "name": "_network",
          "description": "",
          "recommendedTypes": []
        },
        {
          "name": "_networkMembers",
          "description": "",
          "recommendedTypes": []
        }
      ],
      "returnDecorators": [],
      "emittableEvents": [],
      "readOnly": false
    },
    {
      "signature": "getAccruedFees(address[],address)",
      "name": "getAccruedFees",
      "description": "",
      "parameterDecorators": [
        {
          "name": "_members",
          "description": "",
          "recommendedTypes": []
        },
        {
          "name": "_network",
          "description": "",
          "recommendedTypes": []
        }
      ],
      "returnDecorators": [
        {
          "name": "totalFees",
          "description": "",
          "recommendedTypes": [],
          "solidityType": "uint256"
        }
      ],
      "emittableEvents": [],
      "readOnly": true
    },
    {
      "signature": "getCollateralToken()",
      "name": "getCollateralToken",
      "description": "",
      "parameterDecorators": [],
      "returnDecorators": [
        {
          "name": "param0",
          "description": "",
          "recommendedTypes": [],
          "solidityType": "address"
        }
      ],
      "emittableEvents": [],
      "readOnly": true
    },
    {
      "signature": "getUnderwriterPoolStakePercent(address,address)",
      "name": "getUnderwriterPoolStakePercent",
      "description": "",
      "parameterDecorators": [
        {
          "name": "_network",
          "description": "",
          "recommendedTypes": []
        },
        {
          "name": "_networkMember",
          "description": "",
          "recommendedTypes": []
        }
      ],
      "returnDecorators": [
        {
          "name": "param0",
          "description": "",
          "recommendedTypes": [],
          "solidityType": "uint256"
        }
      ],
      "emittableEvents": [],
      "readOnly": false
    },
    {
      "signature": "initialize(address,address,address,uint256)",
      "name": "initialize",
      "description": "",
      "parameterDecorators": [
        {
          "name": "_creditManager",
          "description": "",
          "recommendedTypes": []
        },
        {
          "name": "_creditRoles",
          "description": "",
          "recommendedTypes": []
        },
        {
          "name": "_creditRequest",
          "description": "",
          "recommendedTypes": []
        },
        {
          "name": "_underwriterPercent",
          "description": "",
          "recommendedTypes": []
        }
      ],
      "returnDecorators": [],
      "emittableEvents": [],
      "readOnly": false
    },
    {
      "signature": "owner()",
      "name": "owner",
      "description": "Returns the address of the current owner.",
      "parameterDecorators": [],
      "returnDecorators": [
        {
          "name": "param0",
          "description": "",
          "recommendedTypes": [],
          "solidityType": "address"
        }
      ],
      "emittableEvents": [],
      "readOnly": true
    },
    {
      "signature": "recoverERC20(address,uint256)",
      "name": "recoverERC20",
      "description": "",
      "parameterDecorators": [
        {
          "name": "tokenAddress",
          "description": "",
          "recommendedTypes": []
        },
        {
          "name": "tokenAmount",
          "description": "",
          "recommendedTypes": []
        }
      ],
      "returnDecorators": [],
      "emittableEvents": [],
      "readOnly": false
    },
    {
      "signature": "renounceOwnership()",
      "name": "renounceOwnership",
      "description": "Leaves the contract without owner. It will not be possible to call `onlyOwner` functions anymore. Can only be called by the current owner. NOTE: Renouncing ownership will leave the contract without an owner, thereby removing any functionality that is only available to the owner.",
      "parameterDecorators": [],
      "returnDecorators": [],
      "emittableEvents": [],
      "readOnly": false
    },
    {
      "signature": "transferOwnership(address)",
      "name": "transferOwnership",
      "description": "Transfers ownership of the contract to a new account (`newOwner`). Can only be called by the current owner.",
      "parameterDecorators": [
        {
          "name": "newOwner",
          "description": "",
          "recommendedTypes": []
        }
      ],
      "returnDecorators": [],
      "emittableEvents": [],
      "readOnly": false
    },
    {
      "signature": "underwriterFeePercent()",
      "name": "underwriterFeePercent",
      "description": "",
      "parameterDecorators": [],
      "returnDecorators": [
        {
          "name": "param0",
          "description": "",
          "recommendedTypes": [],
          "solidityType": "uint256"
        }
      ],
      "emittableEvents": [],
      "readOnly": true
    },
    {
      "signature": "updateUnderwriterFeePercent(uint256)",
      "name": "updateUnderwriterFeePercent",
      "description": "",
      "parameterDecorators": [
        {
          "name": "_feePercent",
          "description": "",
          "recommendedTypes": []
        }
      ],
      "returnDecorators": [],
      "emittableEvents": [],
      "readOnly": false
    }
  ]
}