{"schema":"../schema.json","tags":[],"name":"DividendDistributor","description":"","eventDecorators":[{"signature":"Deposit(uint256,uint256)","name":"Deposit","description":"Triggered when the treasury address has been updated.","parameterDecorators":[{"name":"newTreasury","description":"New treasury address.","recommendedTypes":[],"indexed":false},{"name":"oldTreasury","description":"Old treasury address.","recommendedTypes":[],"indexed":false}]},{"signature":"Distribution(address,uint256)","name":"Distribution","description":"Triggered when the treasury address has been updated.","parameterDecorators":[{"name":"newTreasury","description":"New treasury address.","recommendedTypes":[],"indexed":false},{"name":"oldTreasury","description":"Old treasury address.","recommendedTypes":[],"indexed":false}]},{"signature":"DistributionCriteriaUpdated(uint256,uint256)","name":"DistributionCriteriaUpdated","description":"Triggered when the treasury address has been updated.","parameterDecorators":[{"name":"newTreasury","description":"New treasury address.","recommendedTypes":[],"indexed":false},{"name":"oldTreasury","description":"Old treasury address.","recommendedTypes":[],"indexed":false}]},{"signature":"DividendsProcessed(uint256,uint256,uint256)","name":"DividendsProcessed","description":"Triggered when the treasury address has been updated.","parameterDecorators":[{"name":"iterations","description":"","recommendedTypes":[],"indexed":false},{"name":"count","description":"","recommendedTypes":[],"indexed":false},{"name":"index","description":"","recommendedTypes":[],"indexed":false}]},{"signature":"ShareUpdated(address,uint256)","name":"ShareUpdated","description":"Triggered when the treasury address has been updated.","parameterDecorators":[{"name":"newTreasury","description":"New treasury address.","recommendedTypes":[],"indexed":false},{"name":"oldTreasury","description":"Old treasury address.","recommendedTypes":[],"indexed":false}]}],"functionDecorators":[{"signature":"claimDividend()","name":"claimDividend","description":"","parameterDecorators":[],"returnDecorators":[],"emittableEvents":[],"readOnly":false},{"signature":"claimDividendFor(address)","name":"claimDividendFor","description":"","parameterDecorators":[{"name":"shareholder","description":"","recommendedTypes":[]}],"returnDecorators":[],"emittableEvents":[],"readOnly":false},{"signature":"deposit()","name":"deposit","description":"","parameterDecorators":[],"returnDecorators":[],"emittableEvents":[],"readOnly":false},{"signature":"dividendsPerShare()","name":"dividendsPerShare","description":"","parameterDecorators":[],"returnDecorators":[{"name":"param0","description":"","recommendedTypes":[],"solidityType":"uint256"}],"emittableEvents":[],"readOnly":true},{"signature":"dividendsPerShareAccuracyFactor()","name":"dividendsPerShareAccuracyFactor","description":"","parameterDecorators":[],"returnDecorators":[{"name":"param0","description":"","recommendedTypes":[],"solidityType":"uint256"}],"emittableEvents":[],"readOnly":true},{"signature":"getShareholderInfo(address)","name":"getShareholderInfo","description":"","parameterDecorators":[{"name":"shareholder","description":"","recommendedTypes":[]}],"returnDecorators":[{"name":"param0","description":"","recommendedTypes":[],"solidityType":"uint256"},{"name":"param1","description":"","recommendedTypes":[],"solidityType":"uint256"},{"name":"param2","description":"","recommendedTypes":[],"solidityType":"uint256"},{"name":"param3","description":"","recommendedTypes":[],"solidityType":"uint256"}],"emittableEvents":[],"readOnly":true},{"signature":"getUnpaidEarnings(address)","name":"getUnpaidEarnings","description":"","parameterDecorators":[{"name":"shareholder","description":"","recommendedTypes":[]}],"returnDecorators":[{"name":"param0","description":"","recommendedTypes":[],"solidityType":"uint256"}],"emittableEvents":[],"readOnly":true},{"signature":"minDistribution()","name":"minDistribution","description":"","parameterDecorators":[],"returnDecorators":[{"name":"param0","description":"","recommendedTypes":[],"solidityType":"uint256"}],"emittableEvents":[],"readOnly":true},{"signature":"minPeriod()","name":"minPeriod","description":"","parameterDecorators":[],"returnDecorators":[{"name":"param0","description":"","recommendedTypes":[],"solidityType":"uint256"}],"emittableEvents":[],"readOnly":true},{"signature":"process(uint256)","name":"process","description":"","parameterDecorators":[{"name":"gas","description":"","recommendedTypes":[]}],"returnDecorators":[],"emittableEvents":[],"readOnly":false},{"signature":"setDistributionCriteria(uint256,uint256)","name":"setDistributionCriteria","description":"","parameterDecorators":[{"name":"_minPeriod","description":"","recommendedTypes":[]},{"name":"_minDistribution","description":"","recommendedTypes":[]}],"returnDecorators":[],"emittableEvents":[],"readOnly":false},{"signature":"setShare(address,uint256)","name":"setShare","description":"","parameterDecorators":[{"name":"shareholder","description":"","recommendedTypes":[]},{"name":"amount","description":"","recommendedTypes":[]}],"returnDecorators":[],"emittableEvents":[],"readOnly":false},{"signature":"shares(address)","name":"shares","description":"","parameterDecorators":[{"name":"param0","description":"","recommendedTypes":[]}],"returnDecorators":[{"name":"amount","description":"","recommendedTypes":[],"solidityType":"uint256"},{"name":"totalExcluded","description":"","recommendedTypes":[],"solidityType":"uint256"},{"name":"totalRealised","description":"","recommendedTypes":[],"solidityType":"uint256"}],"emittableEvents":[],"readOnly":true},{"signature":"totalDistributed()","name":"totalDistributed","description":"","parameterDecorators":[],"returnDecorators":[{"name":"param0","description":"","recommendedTypes":[],"solidityType":"uint256"}],"emittableEvents":[],"readOnly":true},{"signature":"totalDividends()","name":"totalDividends","description":"","parameterDecorators":[],"returnDecorators":[{"name":"param0","description":"","recommendedTypes":[],"solidityType":"uint256"}],"emittableEvents":[],"readOnly":true},{"signature":"totalShares()","name":"totalShares","description":"","parameterDecorators":[],"returnDecorators":[{"name":"param0","description":"","recommendedTypes":[],"solidityType":"uint256"}],"emittableEvents":[],"readOnly":true}]}