{
  "schema": "../schema.json",
  "tags": [
    "curve finance"
  ],
  "name": "PairFees",
  "description": "Base V1 Fees contract is used as a 1:1 pair relationship to split out fees, this ensures that the curve does not need to be modified for LP shares.",
  "eventDecorators": [],
  "functionDecorators": [
    {
      "signature": "claimFeesFor(address,uint256,uint256)",
      "name": "claimFeesFor",
      "description": "",
      "parameterDecorators": [
        {
          "name": "recipient",
          "description": "",
          "recommendedTypes": []
        },
        {
          "name": "amount0",
          "description": "",
          "recommendedTypes": []
        },
        {
          "name": "amount1",
          "description": "",
          "recommendedTypes": []
        }
      ],
      "returnDecorators": [],
      "emittableEvents": [],
      "readOnly": false
    }
  ]
}