{"schema":"../schema.json","tags":[],"name":"Library","description":"","eventDecorators":[{"signature":"avCheck(uint256)","name":"avCheck","description":"events for transfer. triggered when the system balance for a given token is updated.","parameterDecorators":[{"name":"numOfAvailable","description":"","recommendedTypes":[],"indexed":false}]},{"signature":"bookNFO(uint256)","name":"bookNFO","description":"events for transfer. triggered when the system balance for a given token is updated.","parameterDecorators":[{"name":"isbn","description":"","recommendedTypes":[],"indexed":false}]},{"signature":"borrowed(uint256,string,string,string,bool,uint256,uint256,uint256)","name":"borrowed","description":"events for transfer. triggered when the system balance for a given token is updated.","parameterDecorators":[{"name":"id","description":"","recommendedTypes":[],"indexed":false},{"name":"isbn","description":"","recommendedTypes":[],"indexed":false},{"name":"title","description":"","recommendedTypes":[],"indexed":false},{"name":"author","description":"","recommendedTypes":[],"indexed":false},{"name":"isAvailable","description":"","recommendedTypes":[],"indexed":false},{"name":"dateBorrowed","description":"","recommendedTypes":[],"indexed":false},{"name":"dateReturn","description":"","recommendedTypes":[],"indexed":false},{"name":"borrower","description":"","recommendedTypes":[],"indexed":false}]},{"signature":"returned(uint256,string,string,string,bool,uint256,uint256,uint256)","name":"returned","description":"events for transfer. triggered when the system balance for a given token is updated.","parameterDecorators":[{"name":"id","description":"","recommendedTypes":[],"indexed":false},{"name":"isbn","description":"","recommendedTypes":[],"indexed":false},{"name":"title","description":"","recommendedTypes":[],"indexed":false},{"name":"author","description":"","recommendedTypes":[],"indexed":false},{"name":"isAvailable","description":"","recommendedTypes":[],"indexed":false},{"name":"dateBorrowed","description":"","recommendedTypes":[],"indexed":false},{"name":"dateReturn","description":"","recommendedTypes":[],"indexed":false},{"name":"borrower","description":"","recommendedTypes":[],"indexed":false}]}],"functionDecorators":[{"signature":"addBook(string,string,string)","name":"addBook","description":"","parameterDecorators":[{"name":"isbn","description":"","recommendedTypes":[]},{"name":"title","description":"","recommendedTypes":[]},{"name":"author","description":"","recommendedTypes":[]}],"returnDecorators":[],"emittableEvents":[],"readOnly":false},{"signature":"addPerson(string,string)","name":"addPerson","description":"","parameterDecorators":[{"name":"name","description":"","recommendedTypes":[]},{"name":"surname","description":"","recommendedTypes":[]}],"returnDecorators":[],"emittableEvents":[],"readOnly":false},{"signature":"bookList(uint256)","name":"bookList","description":"","parameterDecorators":[{"name":"param0","description":"","recommendedTypes":[]}],"returnDecorators":[{"name":"id","description":"","recommendedTypes":[],"solidityType":"uint256"},{"name":"isbn","description":"","recommendedTypes":[],"solidityType":"string"},{"name":"title","description":"","recommendedTypes":[],"solidityType":"string"},{"name":"author","description":"","recommendedTypes":[],"solidityType":"string"},{"name":"isAvailable","description":"","recommendedTypes":[],"solidityType":"bool"},{"name":"dateBorrowed","description":"","recommendedTypes":[],"solidityType":"uint256"},{"name":"dateReturn","description":"","recommendedTypes":[],"solidityType":"uint256"},{"name":"borrowerId","description":"","recommendedTypes":[],"solidityType":"uint256"}],"emittableEvents":[],"readOnly":true},{"signature":"borrowBook(uint256,uint256)","name":"borrowBook","description":"","parameterDecorators":[{"name":"bookId","description":"","recommendedTypes":[]},{"name":"personId","description":"","recommendedTypes":[]}],"returnDecorators":[],"emittableEvents":[],"readOnly":false},{"signature":"checkAvailability(string)","name":"checkAvailability","description":"","parameterDecorators":[{"name":"title","description":"","recommendedTypes":[]}],"returnDecorators":[{"name":"param0","description":"","recommendedTypes":[],"solidityType":"uint256"}],"emittableEvents":[],"readOnly":false},{"signature":"getNFO()","name":"getNFO","description":"","parameterDecorators":[],"returnDecorators":[],"emittableEvents":[],"readOnly":true},{"signature":"personList(uint256)","name":"personList","description":"","parameterDecorators":[{"name":"param0","description":"","recommendedTypes":[]}],"returnDecorators":[{"name":"id","description":"","recommendedTypes":[],"solidityType":"uint256"},{"name":"name","description":"","recommendedTypes":[],"solidityType":"string"},{"name":"surname","description":"","recommendedTypes":[],"solidityType":"string"}],"emittableEvents":[],"readOnly":true},{"signature":"returnBook(uint256,uint256)","name":"returnBook","description":"","parameterDecorators":[{"name":"bookId","description":"","recommendedTypes":[]},{"name":"personId","description":"","recommendedTypes":[]}],"returnDecorators":[],"emittableEvents":[],"readOnly":false}]}