{
  "schema": "../schema.json",
  "tags": [],
  "name": "lotterty",
  "description": "",
  "eventDecorators": [
    {
      "signature": "lottertyLog(uint256,uint256,uint256)",
      "name": "lottertyLog",
      "description": "Event for token purchase logging.",
      "parameterDecorators": [
        {
          "name": "poorId",
          "description": "",
          "recommendedTypes": [],
          "indexed": true
        },
        {
          "name": "playerId",
          "description": "",
          "recommendedTypes": [],
          "indexed": true
        },
        {
          "name": "prize",
          "description": "",
          "recommendedTypes": [],
          "indexed": false
        }
      ]
    }
  ],
  "functionDecorators": [
    {
      "signature": "addPoor(string,uint256,uint16)",
      "name": "addPoor",
      "description": "",
      "parameterDecorators": [
        {
          "name": "name_",
          "description": "",
          "recommendedTypes": []
        },
        {
          "name": "id_",
          "description": "",
          "recommendedTypes": []
        },
        {
          "name": "winRate_",
          "description": "",
          "recommendedTypes": []
        }
      ],
      "returnDecorators": [],
      "emittableEvents": [],
      "readOnly": false
    },
    {
      "signature": "magic(uint256,uint256)",
      "name": "magic",
      "description": "",
      "parameterDecorators": [
        {
          "name": "poorId_",
          "description": "",
          "recommendedTypes": []
        },
        {
          "name": "playerId_",
          "description": "",
          "recommendedTypes": []
        }
      ],
      "returnDecorators": [
        {
          "name": "param0",
          "description": "",
          "recommendedTypes": [],
          "solidityType": "bool"
        }
      ],
      "emittableEvents": [],
      "readOnly": false
    },
    {
      "signature": "poors(uint256)",
      "name": "poors",
      "description": "",
      "parameterDecorators": [
        {
          "name": "param0",
          "description": "",
          "recommendedTypes": []
        }
      ],
      "returnDecorators": [
        {
          "name": "name",
          "description": "",
          "recommendedTypes": [],
          "solidityType": "string"
        },
        {
          "name": "id",
          "description": "",
          "recommendedTypes": [],
          "solidityType": "uint256"
        },
        {
          "name": "winRate",
          "description": "",
          "recommendedTypes": [],
          "solidityType": "uint16"
        }
      ],
      "emittableEvents": [],
      "readOnly": true
    },
    {
      "signature": "ran()",
      "name": "ran",
      "description": "",
      "parameterDecorators": [],
      "returnDecorators": [
        {
          "name": "param0",
          "description": "",
          "recommendedTypes": [],
          "solidityType": "uint256"
        }
      ],
      "emittableEvents": [],
      "readOnly": true
    },
    {
      "signature": "ran1()",
      "name": "ran1",
      "description": "",
      "parameterDecorators": [],
      "returnDecorators": [
        {
          "name": "param0",
          "description": "",
          "recommendedTypes": [],
          "solidityType": "uint256"
        }
      ],
      "emittableEvents": [],
      "readOnly": true
    },
    {
      "signature": "ran2()",
      "name": "ran2",
      "description": "",
      "parameterDecorators": [],
      "returnDecorators": [
        {
          "name": "param0",
          "description": "",
          "recommendedTypes": [],
          "solidityType": "bytes32"
        }
      ],
      "emittableEvents": [],
      "readOnly": true
    },
    {
      "signature": "ran3()",
      "name": "ran3",
      "description": "",
      "parameterDecorators": [],
      "returnDecorators": [
        {
          "name": "param0",
          "description": "",
          "recommendedTypes": [],
          "solidityType": "uint256"
        }
      ],
      "emittableEvents": [],
      "readOnly": true
    },
    {
      "signature": "ran4()",
      "name": "ran4",
      "description": "",
      "parameterDecorators": [],
      "returnDecorators": [
        {
          "name": "param0",
          "description": "",
          "recommendedTypes": [],
          "solidityType": "uint256"
        }
      ],
      "emittableEvents": [],
      "readOnly": true
    }
  ]
}