{
  "schema": "../schema.json",
  "tags": [],
  "name": "Mintagram",
  "description": "",
  "eventDecorators": [],
  "functionDecorators": [
    {
      "signature": "addUser(string)",
      "name": "addUser",
      "description": "",
      "parameterDecorators": [
        {
          "name": "_username",
          "description": "",
          "recommendedTypes": []
        }
      ],
      "returnDecorators": [],
      "emittableEvents": [],
      "readOnly": false
    },
    {
      "signature": "admin()",
      "name": "admin",
      "description": "",
      "parameterDecorators": [],
      "returnDecorators": [
        {
          "name": "param0",
          "description": "",
          "recommendedTypes": [],
          "solidityType": "address"
        }
      ],
      "emittableEvents": [],
      "readOnly": true
    },
    {
      "signature": "allPosts(uint256)",
      "name": "allPosts",
      "description": "",
      "parameterDecorators": [
        {
          "name": "param0",
          "description": "",
          "recommendedTypes": []
        }
      ],
      "returnDecorators": [
        {
          "name": "param0",
          "description": "",
          "recommendedTypes": [],
          "solidityType": "address"
        }
      ],
      "emittableEvents": [],
      "readOnly": true
    },
    {
      "signature": "allUsers(address)",
      "name": "allUsers",
      "description": "",
      "parameterDecorators": [
        {
          "name": "param0",
          "description": "",
          "recommendedTypes": []
        }
      ],
      "returnDecorators": [
        {
          "name": "param0",
          "description": "",
          "recommendedTypes": [],
          "solidityType": "address"
        }
      ],
      "emittableEvents": [],
      "readOnly": true
    },
    {
      "signature": "comment(uint256,string)",
      "name": "comment",
      "description": "",
      "parameterDecorators": [
        {
          "name": "_postId",
          "description": "",
          "recommendedTypes": []
        },
        {
          "name": "_comment",
          "description": "",
          "recommendedTypes": []
        }
      ],
      "returnDecorators": [],
      "emittableEvents": [],
      "readOnly": false
    },
    {
      "signature": "getBalance()",
      "name": "getBalance",
      "description": "",
      "parameterDecorators": [],
      "returnDecorators": [
        {
          "name": "param0",
          "description": "",
          "recommendedTypes": [],
          "solidityType": "uint256"
        }
      ],
      "emittableEvents": [],
      "readOnly": true
    },
    {
      "signature": "like(uint256)",
      "name": "like",
      "description": "",
      "parameterDecorators": [
        {
          "name": "_postId",
          "description": "",
          "recommendedTypes": []
        }
      ],
      "returnDecorators": [],
      "emittableEvents": [],
      "readOnly": false
    },
    {
      "signature": "makePost(string)",
      "name": "makePost",
      "description": "",
      "parameterDecorators": [
        {
          "name": "_url",
          "description": "",
          "recommendedTypes": []
        }
      ],
      "returnDecorators": [],
      "emittableEvents": [],
      "readOnly": false
    },
    {
      "signature": "sendAdmin()",
      "name": "sendAdmin",
      "description": "",
      "parameterDecorators": [],
      "returnDecorators": [
        {
          "name": "_data",
          "description": "",
          "recommendedTypes": [],
          "solidityType": "bytes"
        }
      ],
      "emittableEvents": [],
      "readOnly": false
    },
    {
      "signature": "sendGift(uint256)",
      "name": "sendGift",
      "description": "",
      "parameterDecorators": [
        {
          "name": "_postId",
          "description": "",
          "recommendedTypes": []
        }
      ],
      "returnDecorators": [],
      "emittableEvents": [],
      "readOnly": false
    },
    {
      "signature": "totalPosts()",
      "name": "totalPosts",
      "description": "",
      "parameterDecorators": [],
      "returnDecorators": [
        {
          "name": "param0",
          "description": "",
          "recommendedTypes": [],
          "solidityType": "uint256"
        }
      ],
      "emittableEvents": [],
      "readOnly": true
    },
    {
      "signature": "totalUsers()",
      "name": "totalUsers",
      "description": "",
      "parameterDecorators": [],
      "returnDecorators": [
        {
          "name": "param0",
          "description": "",
          "recommendedTypes": [],
          "solidityType": "uint256"
        }
      ],
      "emittableEvents": [],
      "readOnly": true
    }
  ]
}