{
  "schema": "../schema.json",
  "tags": [],
  "name": "MultiWallet",
  "description": "",
  "eventDecorators": [],
  "functionDecorators": [
    {
      "signature": "changeWallet1(address)",
      "name": "changeWallet1",
      "description": "",
      "parameterDecorators": [
        {
          "name": "_newWallet",
          "description": "",
          "recommendedTypes": []
        }
      ],
      "returnDecorators": [],
      "emittableEvents": [],
      "readOnly": false
    },
    {
      "signature": "changeWallet2(address)",
      "name": "changeWallet2",
      "description": "",
      "parameterDecorators": [
        {
          "name": "_newWallet",
          "description": "",
          "recommendedTypes": []
        }
      ],
      "returnDecorators": [],
      "emittableEvents": [],
      "readOnly": false
    },
    {
      "signature": "changeWallet3(address)",
      "name": "changeWallet3",
      "description": "",
      "parameterDecorators": [
        {
          "name": "_newWallet",
          "description": "",
          "recommendedTypes": []
        }
      ],
      "returnDecorators": [],
      "emittableEvents": [],
      "readOnly": false
    },
    {
      "signature": "changeWallet4(address)",
      "name": "changeWallet4",
      "description": "",
      "parameterDecorators": [
        {
          "name": "_newWallet",
          "description": "",
          "recommendedTypes": []
        }
      ],
      "returnDecorators": [],
      "emittableEvents": [],
      "readOnly": false
    },
    {
      "signature": "changeWallet5(address)",
      "name": "changeWallet5",
      "description": "",
      "parameterDecorators": [
        {
          "name": "_newWallet",
          "description": "",
          "recommendedTypes": []
        }
      ],
      "returnDecorators": [],
      "emittableEvents": [],
      "readOnly": false
    },
    {
      "signature": "divide()",
      "name": "divide",
      "description": "",
      "parameterDecorators": [],
      "returnDecorators": [],
      "emittableEvents": [],
      "readOnly": false
    }
  ]
}