{
  "schema": "../schema.json",
  "tags": [],
  "name": "quickEventTest",
  "description": "",
  "eventDecorators": [
    {
      "signature": "someRandomEvent(address,uint256)",
      "name": "someRandomEvent",
      "description": "event emitted when first initializing the Market factory.",
      "parameterDecorators": [
        {
          "name": "_me",
          "description": "",
          "recommendedTypes": [],
          "indexed": true
        },
        {
          "name": "_value",
          "description": "",
          "recommendedTypes": [],
          "indexed": false
        }
      ]
    }
  ],
  "functionDecorators": [
    {
      "signature": "giveMeAnAddress(address)",
      "name": "giveMeAnAddress",
      "description": "",
      "parameterDecorators": [
        {
          "name": "_add",
          "description": "",
          "recommendedTypes": []
        }
      ],
      "returnDecorators": [],
      "emittableEvents": [],
      "readOnly": false
    },
    {
      "signature": "raiseEvent()",
      "name": "raiseEvent",
      "description": "",
      "parameterDecorators": [],
      "returnDecorators": [],
      "emittableEvents": [],
      "readOnly": false
    }
  ]
}