{
  "schema": "../schema.json",
  "tags": [],
  "name": "RandomNumberConsumer",
  "description": "",
  "eventDecorators": [
    {
      "signature": "NewAddress(address,uint256,uint256)",
      "name": "NewAddress",
      "description": "Event emitted for each executed trade.",
      "parameterDecorators": [
        {
          "name": "_from",
          "description": "",
          "recommendedTypes": [],
          "indexed": false
        },
        {
          "name": "_value",
          "description": "",
          "recommendedTypes": [],
          "indexed": false
        },
        {
          "name": "_poolIndex",
          "description": "",
          "recommendedTypes": [],
          "indexed": true
        }
      ]
    },
    {
      "signature": "NewPool(uint256,uint256)",
      "name": "NewPool",
      "description": "Event emitted for each executed trade.",
      "parameterDecorators": [
        {
          "name": "_nextRunDate",
          "description": "",
          "recommendedTypes": [],
          "indexed": false
        },
        {
          "name": "_poolIndex",
          "description": "",
          "recommendedTypes": [],
          "indexed": true
        }
      ]
    },
    {
      "signature": "NewWinner(address,uint256,uint256)",
      "name": "NewWinner",
      "description": "Event emitted for each executed trade.",
      "parameterDecorators": [
        {
          "name": "_from",
          "description": "",
          "recommendedTypes": [],
          "indexed": false
        },
        {
          "name": "_value",
          "description": "",
          "recommendedTypes": [],
          "indexed": false
        },
        {
          "name": "_poolIndex",
          "description": "",
          "recommendedTypes": [],
          "indexed": true
        }
      ]
    }
  ],
  "functionDecorators": [
    {
      "signature": "activePools(uint256)",
      "name": "activePools",
      "description": "",
      "parameterDecorators": [
        {
          "name": "param0",
          "description": "",
          "recommendedTypes": []
        }
      ],
      "returnDecorators": [
        {
          "name": "param0",
          "description": "",
          "recommendedTypes": [],
          "solidityType": "uint256"
        }
      ],
      "emittableEvents": [],
      "readOnly": true
    },
    {
      "signature": "addAddress(uint256)",
      "name": "addAddress",
      "description": "",
      "parameterDecorators": [
        {
          "name": "poolIndex",
          "description": "",
          "recommendedTypes": []
        }
      ],
      "returnDecorators": [],
      "emittableEvents": [],
      "readOnly": false
    },
    {
      "signature": "addPool(uint256,uint256,uint256)",
      "name": "addPool",
      "description": "",
      "parameterDecorators": [
        {
          "name": "_nextRunDate",
          "description": "",
          "recommendedTypes": []
        },
        {
          "name": "_minumumValue",
          "description": "",
          "recommendedTypes": []
        },
        {
          "name": "_ownerPercentFee",
          "description": "",
          "recommendedTypes": []
        }
      ],
      "returnDecorators": [],
      "emittableEvents": [],
      "readOnly": false
    },
    {
      "signature": "pools(uint256)",
      "name": "pools",
      "description": "",
      "parameterDecorators": [
        {
          "name": "param0",
          "description": "",
          "recommendedTypes": []
        }
      ],
      "returnDecorators": [
        {
          "name": "entryCount",
          "description": "",
          "recommendedTypes": [],
          "solidityType": "int256"
        },
        {
          "name": "randomResult",
          "description": "",
          "recommendedTypes": [],
          "solidityType": "uint256"
        },
        {
          "name": "winningAddress",
          "description": "",
          "recommendedTypes": [],
          "solidityType": "address"
        },
        {
          "name": "owner",
          "description": "",
          "recommendedTypes": [],
          "solidityType": "address"
        },
        {
          "name": "nextRunDate",
          "description": "",
          "recommendedTypes": [],
          "solidityType": "uint256"
        },
        {
          "name": "minumumValue",
          "description": "",
          "recommendedTypes": [],
          "solidityType": "uint256"
        },
        {
          "name": "ownerPercentFee",
          "description": "",
          "recommendedTypes": [],
          "solidityType": "uint256"
        },
        {
          "name": "active",
          "description": "",
          "recommendedTypes": [],
          "solidityType": "bool"
        }
      ],
      "emittableEvents": [],
      "readOnly": true
    },
    {
      "signature": "rawFulfillRandomness(bytes32,uint256)",
      "name": "rawFulfillRandomness",
      "description": "",
      "parameterDecorators": [
        {
          "name": "requestId",
          "description": "",
          "recommendedTypes": []
        },
        {
          "name": "randomness",
          "description": "",
          "recommendedTypes": []
        }
      ],
      "returnDecorators": [],
      "emittableEvents": [],
      "readOnly": false
    },
    {
      "signature": "runEntries(uint256,uint256)",
      "name": "runEntries",
      "description": "",
      "parameterDecorators": [
        {
          "name": "userProvidedSeed",
          "description": "",
          "recommendedTypes": []
        },
        {
          "name": "poolIndex",
          "description": "",
          "recommendedTypes": []
        }
      ],
      "returnDecorators": [],
      "emittableEvents": [],
      "readOnly": false
    }
  ]
}