{"schema":"../schema.json","tags":[],"name":"TimestampLogger","description":"","eventDecorators":[],"functionDecorators":[{"signature":"addHash(string,string,string)","name":"addHash","description":"","parameterDecorators":[{"name":"identifier","description":"","recommendedTypes":[]},{"name":"hash","description":"","recommendedTypes":[]},{"name":"signedHash","description":"","recommendedTypes":[]}],"returnDecorators":[],"emittableEvents":[],"readOnly":false},{"signature":"getHash(string)","name":"getHash","description":"","parameterDecorators":[{"name":"identifier","description":"","recommendedTypes":[]}],"returnDecorators":[{"name":"param0","description":"","recommendedTypes":[],"solidityType":"tuple"}],"emittableEvents":[],"readOnly":true}]}