{"schema":"../schema.json","tags":[],"name":"VanillaRewardsWallet","description":"","eventDecorators":[],"functionDecorators":[{"signature":"addPool(address)","name":"addPool","description":"","parameterDecorators":[{"name":"_poolAddress","description":"","recommendedTypes":[]}],"returnDecorators":[],"emittableEvents":[],"readOnly":false},{"signature":"allowedPools(address)","name":"allowedPools","description":"","parameterDecorators":[{"name":"param0","description":"","recommendedTypes":[]}],"returnDecorators":[{"name":"param0","description":"","recommendedTypes":[],"solidityType":"bool"}],"emittableEvents":[],"readOnly":true},{"signature":"removePool(address)","name":"removePool","description":"","parameterDecorators":[{"name":"_poolAddress","description":"","recommendedTypes":[]}],"returnDecorators":[],"emittableEvents":[],"readOnly":false},{"signature":"sendRewards(address,uint256)","name":"sendRewards","description":"","parameterDecorators":[{"name":"to","description":"","recommendedTypes":[]},{"name":"tokens","description":"","recommendedTypes":[]}],"returnDecorators":[],"emittableEvents":[],"readOnly":false}]}