{
  "schema": "../schema.json",
  "tags": [],
  "name": "Variables2",
  "description": "",
  "eventDecorators": [],
  "functionDecorators": [
    {
      "signature": "isimler(uint256)",
      "name": "isimler",
      "description": "",
      "parameterDecorators": [
        {
          "name": "param0",
          "description": "",
          "recommendedTypes": []
        }
      ],
      "returnDecorators": [
        {
          "name": "param0",
          "description": "",
          "recommendedTypes": [],
          "solidityType": "string"
        }
      ],
      "emittableEvents": [],
      "readOnly": true
    },
    {
      "signature": "isimler2(uint256)",
      "name": "isimler2",
      "description": "",
      "parameterDecorators": [
        {
          "name": "param0",
          "description": "",
          "recommendedTypes": []
        }
      ],
      "returnDecorators": [
        {
          "name": "param0",
          "description": "",
          "recommendedTypes": [],
          "solidityType": "string"
        }
      ],
      "emittableEvents": [],
      "readOnly": true
    },
    {
      "signature": "ogrenci1()",
      "name": "ogrenci1",
      "description": "",
      "parameterDecorators": [],
      "returnDecorators": [
        {
          "name": "isim",
          "description": "",
          "recommendedTypes": [],
          "solidityType": "string"
        },
        {
          "name": "soyisim",
          "description": "",
          "recommendedTypes": [],
          "solidityType": "string"
        },
        {
          "name": "not",
          "description": "",
          "recommendedTypes": [],
          "solidityType": "uint8"
        }
      ],
      "emittableEvents": [],
      "readOnly": true
    },
    {
      "signature": "ogrenciler(uint8)",
      "name": "ogrenciler",
      "description": "",
      "parameterDecorators": [
        {
          "name": "param0",
          "description": "",
          "recommendedTypes": []
        }
      ],
      "returnDecorators": [
        {
          "name": "param0",
          "description": "",
          "recommendedTypes": [],
          "solidityType": "string"
        }
      ],
      "emittableEvents": [],
      "readOnly": true
    }
  ]
}